{
  "cover_letter": {
    "from": "김은혜 · dmsgp2627@naver.com · +82-10-2627-1356 · github.com/eeeunhey",
    "to": "채용담당자님 / [회사명] [지원직무]",
    "paragraphs": [
      "안녕하세요. 웹·백엔드·AI를 잇는 주니어 개발자 김은혜입니다.",
      "왜 이 회사인가 — [제품/팀 미션]과 [기술환경]이 제 경험과 맞닿아 있다고 판단했습니다.",
      "왜 저인가 — 분석 로딩 42% 단축, 재학습 35% 감소, 대용량 업로드 성공률 99%+를 만들었습니다.",
      "90일 계획 — ① 계측/병목 진단 ② 렌더링·차트·업로드 최적화 ③ 전환율 개선 실험(AB).",
      "읽기 쉬운 인터페이스와 측정 가능한 성과로 기여하겠습니다. 감사합니다."
    ],
    "short": "김은혜입니다. React/Java로 분석 로딩 42%↓·재학습 35%↓ 성과. 90일 내 계측→튜닝→실험으로 전환율 개선 제안드리겠습니다."
  }
}
